Metadata-Version: 1.1
Name: tp-django-tables2-reports
Version: 0.0.12
Summary: With django-tables2-reports you can get a report (CSV, XLS) of any django-tables2 with minimal changes to your project. Fork of abondened https://github.com/goinnn/django-tables2-reports
Home-page: https://github.com/TriplePoint-Software/django-tables2-reports
Author: Max Syabro
Author-email: maxim@syabro.com
License: LGPL 3
Keywords: django,tables,django-tables2,reports,CSV,XLS
Platform: UNKNOWN
Classifier: Development Status :: 4 - Beta
Classifier: Framework :: Django
Classifier: License :: OSI Approved :: GNU Library or Lesser General Public License (LGPL)
Classifier: Programming Language :: Python :: 2
Classifier: Programming Language :: Python :: 3
